pandas_datatypes/__init__.py
pandas_datatypes/data_types.py
pandas_datatypes-1.2.0.dist-info/METADATA
pandas_datatypes-1.2.0.dist-info/WHEEL
pandas_datatypes-1.2.0.dist-info/top_level.txt
pandas_datatypes-1.2.0.dist-info/RECORD
