Metadata-Version: 2.1
Name: pandas_datatypes
Version: 1.2.0
Summary: A library for getting correct datatype from pandas DataFrame
Author: Brajesh
Requires-Dist: pandas
